sqlalchemy_ibmi/__init__.py
sqlalchemy_ibmi/base.py
sqlalchemy_ibmi/constants.py
sqlalchemy_ibmi/requirements.py
dt_sqlalchemy_ibmi-0.9.5.dev0.dist-info/entry_points.txt
dt_sqlalchemy_ibmi-0.9.5.dev0.dist-info/LICENSE
dt_sqlalchemy_ibmi-0.9.5.dev0.dist-info/METADATA
dt_sqlalchemy_ibmi-0.9.5.dev0.dist-info/WHEEL
dt_sqlalchemy_ibmi-0.9.5.dev0.dist-info/RECORD
